{
  "meta": {
    "description": "イベントの種：AIはこれを元に自由に展開する",
    "version": "1.0",
    "rule": "イベントは種であり台本ではない。AIが状況に応じて自然に膨らませること"
  },

  "daily": {
    "description": "日常イベント：商店街での自然な遭遇",
    "base_encounter_rate": "段階A-C:低 / D-F:中 / G-J:高",
    "seeds": [
      "買い物中にばったり会う",
      "店の前を通りかかったら声をかけられる",
      "雨宿りで偶然一緒になる",
      "商店街の掃除を一緒にやることになる",
      "隣の店の人から噂話を聞く",
      "荷物を持つのを手伝う",
      "迷子の子供を一緒に探す",
      "停電で商店街が暗くなる",
      "野良猫が二人の間を通る",
      "同じ弁当屋で鉢合わせる"
    ]
  },

  "seasonal": {
    "description": "季節イベント：月に応じた特別な空気",
    "seeds": [
      { "months": [3,4], "seed": "桜並木、新生活、春の匂い" },
      { "months": [7,8], "seed": "夏祭り、花火、浴衣、かき氷" },
      { "months": [10],  "seed": "ハロウィン、商店街の仮装大会" },
      { "months": [12],  "seed": "クリスマス、イルミネーション、プレゼント" },
      { "months": [2],   "seed": "バレンタイン、チョコ、雪の日" }
    ]
  },
  "romance": {
    "description": "恋愛イベント：段階に応じた特別な瞬間",
    "min_stage": "E",
    "seeds": [
      "二人きりで夕焼けを見る",
      "相手の寝顔を見てしまう",
      "手が偶然触れる",
      "他の異性と話しているのを見て胸がざわつく",
      "プレゼントを渡す／もらう",
      "酔って本音が漏れる"
    ]
  },
   "wound": {
    "description": "心の傷イベント：過去のトラウマに触れる瞬間",
    "min_stage": "F",
    "rule": "絶対に軽く扱わない。段階が足りなければ壁を作って拒絶する",
    "seeds": [
      "ふとした言葉で表情が曇る",
      "ある場所を避けている理由",
      "雨の日に様子がおかしくなる",
      "昔の写真が落ちる",
      "誰かの名前に過剰反応する",
      "夜中に一人で泣いている"
    ]
  }
}